cleandb/__init__.py
cleandb/main.py
cleandb/mdb_ScreenBuffer.py
cleandb/mdb_control_file_visibility.py
cleandb/mdb_core.py
cleandb/mdb_date_change.py
cleandb/mdb_loop_progress.py
cleandb/mdb_max_clear.py
cleandb/mdb_mini_guide.py
cleandb/mdb_others.py
cleandb/mdb_pretty_print.py
cleandb/mdb_session_id_generator.py
cleandb/mdb_validations.py
cleandb/mdb_wait_queue.py
cleandb-5.0.3.dist-info/METADATA
cleandb-5.0.3.dist-info/WHEEL
cleandb-5.0.3.dist-info/top_level.txt
cleandb-5.0.3.dist-info/RECORD
