Metadata-Version: 2.4
Name: cleandb
Version: 5.0.3
Summary: easy to set up alternative to SQl, bugs and leak proof by design and also support multiple console interactions
Author: henry
Author-email: osas2henry@gmail.com
Classifier: Programming Language :: Python :: 3
Classifier: Operating System :: OS Independent
Classifier: License :: OSI Approved :: MIT License
Requires-Python: >=3.7
Dynamic: author
Dynamic: author-email
Dynamic: classifier
Dynamic: description
Dynamic: description-content-type
Dynamic: requires-python
Dynamic: summary
